{
  "users": {
    "Luze": {
      "total_mem_accum": 241569712,
      "total_gb_hours": 3931.7986979166667,
      "samples": 2220,
      "avg_mem": 108815.18558558558,
      "last_sample_mem": 180696,
      "last_seen": "2025-10-28T02:41:02.573593Z",
      "first_seen": "2025-10-25T04:51:02.161833Z",
      "all_machines": [
        "achtung-biggpu",
        "achtung-biggpu (CPU)"
      ],
      "last_sample_machines": [
        "achtung-biggpu"
      ],
      "raw_users_seen": [
        "luzsun"
      ]
    },
    "Shuyi": {
      "total_mem_accum": 283728100,
      "total_gb_hours": 4617.970377604167,
      "samples": 2832,
      "avg_mem": 100186.47598870056,
      "last_sample_mem": 92550,
      "last_seen": "2025-10-28T02:41:02.573593Z",
      "first_seen": "2025-10-25T04:52:02.687274Z",
      "all_machines": [
        "achtung-gamma"
      ],
      "last_sample_machines": [
        "achtung-gamma"
      ],
      "raw_users_seen": [
        "shuyilin"
      ]
    },
    "Sae": {
      "total_mem_accum": 144305702,
      "total_gb_hours": 2348.725618489583,
      "samples": 1454,
      "avg_mem": 99247.3878954608,
      "last_sample_mem": 139272,
      "last_seen": "2025-10-28T02:41:02.573593Z",
      "first_seen": "2025-10-25T04:52:02.687274Z",
      "all_machines": [
        "achtung-gamma"
      ],
      "last_sample_machines": [
        "achtung-gamma"
      ],
      "raw_users_seen": [
        "saefurukawa"
      ]
    },
    "Anshuman": {
      "total_mem_accum": 466102,
      "total_gb_hours": 7.586295572916667,
      "samples": 11,
      "avg_mem": 42372.90909090909,
      "last_sample_mem": 41740,
      "last_seen": "2025-10-25T19:11:02.872921Z",
      "first_seen": "2025-10-25T19:01:02.124980Z",
      "all_machines": [
        "achtung-gamma"
      ],
      "last_sample_machines": [
        "achtung-gamma"
      ],
      "raw_users_seen": [
        "anshumansuri"
      ]
    },
    "Anqi": {
      "total_mem_accum": 16035382,
      "total_gb_hours": 260.99254557291664,
      "samples": 176,
      "avg_mem": 91110.125,
      "last_sample_mem": 175368,
      "last_seen": "2025-10-27T22:12:02.215110Z",
      "first_seen": "2025-10-27T19:15:02.411105Z",
      "all_machines": [
        "achtung-gamma"
      ],
      "last_sample_machines": [
        "achtung-gamma"
      ],
      "raw_users_seen": [
        "aglc"
      ]
    }
  },
  "cluster": {
    "total_capacity_accum": 2663425512,
    "samples": 4206,
    "last_capacity": 727288,
    "last_updated": "2025-10-28T02:41:02.573593Z"
  },
  "updated_at": "2025-10-28T02:41:02.573593Z"
}