{
  "users": {
    "Luze": {
      "total_mem_accum": 46874614,
      "total_gb_hours": 762.9331705729167,
      "samples": 404,
      "avg_mem": 116026.27227722772,
      "last_sample_mem": 84120,
      "last_seen": "2025-10-25T21:10:02.072895Z",
      "first_seen": "2025-10-25T04:51:02.161833Z",
      "all_machines": [
        "achtung-biggpu"
      ],
      "last_sample_machines": [
        "achtung-biggpu"
      ],
      "raw_users_seen": [
        "luzsun"
      ]
    },
    "Shuyi": {
      "total_mem_accum": 27425382,
      "total_gb_hours": 446.37666015625,
      "samples": 517,
      "avg_mem": 53047.160541586076,
      "last_sample_mem": 92550,
      "last_seen": "2025-10-25T21:10:02.072895Z",
      "first_seen": "2025-10-25T04:52:02.687274Z",
      "all_machines": [
        "achtung-gamma"
      ],
      "last_sample_machines": [
        "achtung-gamma"
      ],
      "raw_users_seen": [
        "shuyilin"
      ]
    },
    "Sae": {
      "total_mem_accum": 4188780,
      "total_gb_hours": 68.1767578125,
      "samples": 54,
      "avg_mem": 77570.0,
      "last_sample_mem": 77570,
      "last_seen": "2025-10-25T05:45:02.715235Z",
      "first_seen": "2025-10-25T04:52:02.687274Z",
      "all_machines": [
        "achtung-gamma"
      ],
      "last_sample_machines": [
        "achtung-gamma"
      ],
      "raw_users_seen": [
        "saefurukawa"
      ]
    },
    "Anshuman": {
      "total_mem_accum": 466102,
      "total_gb_hours": 7.586295572916667,
      "samples": 11,
      "avg_mem": 42372.90909090909,
      "last_sample_mem": 41740,
      "last_seen": "2025-10-25T19:11:02.872921Z",
      "first_seen": "2025-10-25T19:01:02.124980Z",
      "all_machines": [
        "achtung-gamma"
      ],
      "last_sample_machines": [
        "achtung-gamma"
      ],
      "raw_users_seen": [
        "anshumansuri"
      ]
    }
  },
  "cluster": {
    "total_capacity_accum": 628728952,
    "samples": 994,
    "last_capacity": 653584,
    "last_updated": "2025-10-25T21:10:02.072895Z"
  },
  "updated_at": "2025-10-25T21:10:02.072895Z"
}