{
  "users": {
    "Luze": {
      "total_mem_accum": 104024822,
      "total_gb_hours": 1693.1123372395834,
      "samples": 992,
      "avg_mem": 104863.73185483871,
      "last_sample_mem": 42222,
      "last_seen": "2025-10-26T20:34:02.349723Z",
      "first_seen": "2025-10-25T04:51:02.161833Z",
      "all_machines": [
        "achtung-biggpu"
      ],
      "last_sample_machines": [
        "achtung-biggpu"
      ],
      "raw_users_seen": [
        "luzsun"
      ]
    },
    "Shuyi": {
      "total_mem_accum": 189500646,
      "total_gb_hours": 3084.32041015625,
      "samples": 1701,
      "avg_mem": 111405.43562610229,
      "last_sample_mem": 116396,
      "last_seen": "2025-10-26T20:34:02.349723Z",
      "first_seen": "2025-10-25T04:52:02.687274Z",
      "all_machines": [
        "achtung-gamma"
      ],
      "last_sample_machines": [
        "achtung-gamma"
      ],
      "raw_users_seen": [
        "shuyilin"
      ]
    },
    "Sae": {
      "total_mem_accum": 14277652,
      "total_gb_hours": 232.38365885416667,
      "samples": 230,
      "avg_mem": 62076.747826086954,
      "last_sample_mem": 58054,
      "last_seen": "2025-10-26T20:34:02.349723Z",
      "first_seen": "2025-10-25T04:52:02.687274Z",
      "all_machines": [
        "achtung-gamma"
      ],
      "last_sample_machines": [
        "achtung-gamma"
      ],
      "raw_users_seen": [
        "saefurukawa"
      ]
    },
    "Anshuman": {
      "total_mem_accum": 466102,
      "total_gb_hours": 7.586295572916667,
      "samples": 11,
      "avg_mem": 42372.90909090909,
      "last_sample_mem": 41740,
      "last_seen": "2025-10-25T19:11:02.872921Z",
      "first_seen": "2025-10-25T19:01:02.124980Z",
      "all_machines": [
        "achtung-gamma"
      ],
      "last_sample_machines": [
        "achtung-gamma"
      ],
      "raw_users_seen": [
        "anshumansuri"
      ]
    }
  },
  "cluster": {
    "total_capacity_accum": 1527752672,
    "samples": 2399,
    "last_capacity": 579880,
    "last_updated": "2025-10-26T20:34:02.349723Z"
  },
  "updated_at": "2025-10-26T20:34:02.349723Z"
}