{
  "users": {
    "Luze": {
      "total_mem_accum": 107787208,
      "total_gb_hours": 1754.3490885416666,
      "samples": 1032,
      "avg_mem": 104444.96899224806,
      "last_sample_mem": 125862,
      "last_seen": "2025-10-26T21:32:01.925485Z",
      "first_seen": "2025-10-25T04:51:02.161833Z",
      "all_machines": [
        "achtung-biggpu"
      ],
      "last_sample_machines": [
        "achtung-biggpu"
      ],
      "raw_users_seen": [
        "luzsun"
      ]
    },
    "Shuyi": {
      "total_mem_accum": 195032652,
      "total_gb_hours": 3174.3595703125,
      "samples": 1759,
      "avg_mem": 110877.00511654349,
      "last_sample_mem": 92552,
      "last_seen": "2025-10-26T21:32:01.925485Z",
      "first_seen": "2025-10-25T04:52:02.687274Z",
      "all_machines": [
        "achtung-gamma"
      ],
      "last_sample_machines": [
        "achtung-gamma"
      ],
      "raw_users_seen": [
        "shuyilin"
      ]
    },
    "Sae": {
      "total_mem_accum": 17438258,
      "total_gb_hours": 283.82581380208336,
      "samples": 288,
      "avg_mem": 60549.506944444445,
      "last_sample_mem": 40700,
      "last_seen": "2025-10-26T21:32:01.925485Z",
      "first_seen": "2025-10-25T04:52:02.687274Z",
      "all_machines": [
        "achtung-gamma"
      ],
      "last_sample_machines": [
        "achtung-gamma"
      ],
      "raw_users_seen": [
        "saefurukawa"
      ]
    },
    "Anshuman": {
      "total_mem_accum": 466102,
      "total_gb_hours": 7.586295572916667,
      "samples": 11,
      "avg_mem": 42372.90909090909,
      "last_sample_mem": 41740,
      "last_seen": "2025-10-25T19:11:02.872921Z",
      "first_seen": "2025-10-25T19:01:02.124980Z",
      "all_machines": [
        "achtung-gamma"
      ],
      "last_sample_machines": [
        "achtung-gamma"
      ],
      "raw_users_seen": [
        "anshumansuri"
      ]
    }
  },
  "cluster": {
    "total_capacity_accum": 1563572256,
    "samples": 2457,
    "last_capacity": 727288,
    "last_updated": "2025-10-26T21:32:01.925485Z"
  },
  "updated_at": "2025-10-26T21:32:01.925485Z"
}