{
  "users": {
    "Luze": {
      "total_mem_accum": 25532920,
      "total_gb_hours": 415.5748697916667,
      "samples": 198,
      "avg_mem": 128954.14141414141,
      "last_sample_mem": 128358,
      "last_seen": "2025-10-25T08:56:02.091688Z",
      "first_seen": "2025-10-25T04:51:02.161833Z",
      "all_machines": [
        "achtung-biggpu"
      ],
      "last_sample_machines": [
        "achtung-biggpu"
      ],
      "raw_users_seen": [
        "luzsun"
      ]
    },
    "Shuyi": {
      "total_mem_accum": 14465540,
      "total_gb_hours": 235.44173177083334,
      "samples": 239,
      "avg_mem": 60525.271966527194,
      "last_sample_mem": 74830,
      "last_seen": "2025-10-25T08:56:02.091688Z",
      "first_seen": "2025-10-25T04:52:02.687274Z",
      "all_machines": [
        "achtung-gamma"
      ],
      "last_sample_machines": [
        "achtung-gamma"
      ],
      "raw_users_seen": [
        "shuyilin"
      ]
    },
    "Sae": {
      "total_mem_accum": 4188780,
      "total_gb_hours": 68.1767578125,
      "samples": 54,
      "avg_mem": 77570.0,
      "last_sample_mem": 77570,
      "last_seen": "2025-10-25T05:45:02.715235Z",
      "first_seen": "2025-10-25T04:52:02.687274Z",
      "all_machines": [
        "achtung-gamma"
      ],
      "last_sample_machines": [
        "achtung-gamma"
      ],
      "raw_users_seen": [
        "saefurukawa"
      ]
    }
  },
  "cluster": {
    "total_capacity_accum": 159562856,
    "samples": 260,
    "last_capacity": 727288,
    "last_updated": "2025-10-25T08:56:02.091688Z"
  },
  "updated_at": "2025-10-25T08:56:02.091688Z"
}