{
  "users": {
    "Luze": {
      "total_mem_accum": 1721810418,
      "total_gb_hours": 28024.25810546875,
      "samples": 12502,
      "avg_mem": 137722.79779235323,
      "last_sample_mem": 129378,
      "last_seen": "2025-11-12T16:58:02.747316Z",
      "first_seen": "2025-10-25T04:51:02.161833Z",
      "all_machines": [
        "achtung-biggpu",
        "achtung-biggpu (CPU)",
        "achtung-gamma"
      ],
      "last_sample_machines": [
        "achtung-biggpu"
      ],
      "raw_users_seen": [
        "luzsun"
      ]
    },
    "Shuyi": {
      "total_mem_accum": 773229778,
      "total_gb_hours": 12585.120084635417,
      "samples": 6448,
      "avg_mem": 119917.76954094293,
      "last_sample_mem": 92552,
      "last_seen": "2025-11-07T22:40:02.341893Z",
      "first_seen": "2025-10-25T04:52:02.687274Z",
      "all_machines": [
        "achtung-gamma",
        "achtung-gamma (CPU)"
      ],
      "last_sample_machines": [
        "achtung-gamma"
      ],
      "raw_users_seen": [
        "shuyilin"
      ]
    },
    "Sae": {
      "total_mem_accum": 744293760,
      "total_gb_hours": 12114.15625,
      "samples": 7781,
      "avg_mem": 95655.28338259863,
      "last_sample_mem": 133706,
      "last_seen": "2025-11-12T17:00:02.547159Z",
      "first_seen": "2025-10-25T04:52:02.687274Z",
      "all_machines": [
        "achtung-biggpu",
        "achtung-gamma",
        "achtung-gamma (CPU)"
      ],
      "last_sample_machines": [
        "achtung-gamma"
      ],
      "raw_users_seen": [
        "saefurukawa"
      ]
    },
    "Anshuman": {
      "total_mem_accum": 226552318,
      "total_gb_hours": 3687.374967447917,
      "samples": 2851,
      "avg_mem": 79464.1592423711,
      "last_sample_mem": 1244,
      "last_seen": "2025-11-12T15:15:02.652435Z",
      "first_seen": "2025-10-25T19:01:02.124980Z",
      "all_machines": [
        "achtung-gamma",
        "achtung-gamma (CPU)"
      ],
      "last_sample_machines": [
        "achtung-gamma"
      ],
      "raw_users_seen": [
        "anshumansuri"
      ]
    },
    "Anqi": {
      "total_mem_accum": 181040972,
      "total_gb_hours": 2946.630403645833,
      "samples": 1248,
      "avg_mem": 145064.8814102564,
      "last_sample_mem": 85966,
      "last_seen": "2025-11-12T00:31:02.398268Z",
      "first_seen": "2025-10-27T19:15:02.411105Z",
      "all_machines": [
        "achtung-biggpu",
        "achtung-biggpu (CPU)",
        "achtung-gamma"
      ],
      "last_sample_machines": [
        "achtung-gamma"
      ],
      "raw_users_seen": [
        "aglc"
      ]
    },
    "unknown": {
      "total_mem_accum": 92656,
      "total_gb_hours": 1.5080729166666667,
      "samples": 2,
      "avg_mem": 46328.0,
      "last_sample_mem": 622,
      "last_seen": "2025-11-04T22:01:02.385832Z",
      "first_seen": "2025-10-28T16:44:02.695215Z",
      "all_machines": [
        "achtung-gamma"
      ],
      "last_sample_machines": [
        "achtung-gamma"
      ],
      "raw_users_seen": [
        "unknown"
      ]
    },
    "Georgios": {
      "total_mem_accum": 1409048388,
      "total_gb_hours": 22933.7302734375,
      "samples": 12927,
      "avg_mem": 109000.41680204224,
      "last_sample_mem": 86102,
      "last_seen": "2025-11-12T17:00:02.547159Z",
      "first_seen": "2025-10-28T20:31:02.515616Z",
      "all_machines": [
        "achtung-gamma"
      ],
      "last_sample_machines": [
        "achtung-gamma"
      ],
      "raw_users_seen": [
        "georgios"
      ]
    },
    "Evan": {
      "total_mem_accum": 507948510,
      "total_gb_hours": 8267.39111328125,
      "samples": 4934,
      "avg_mem": 102948.62383461694,
      "last_sample_mem": 86112,
      "last_seen": "2025-11-12T17:00:02.547159Z",
      "first_seen": "2025-10-28T21:09:02.469455Z",
      "all_machines": [
        "achtung-gamma"
      ],
      "last_sample_machines": [
        "achtung-gamma"
      ],
      "raw_users_seen": [
        "roseev"
      ]
    },
    "Harsh": {
      "total_mem_accum": 542036,
      "total_gb_hours": 8.822200520833333,
      "samples": 205,
      "avg_mem": 2644.0780487804877,
      "last_sample_mem": 20176,
      "last_seen": "2025-11-11T20:30:02.604006Z",
      "first_seen": "2025-11-09T23:38:02.553566Z",
      "all_machines": [
        "achtung-gamma"
      ],
      "last_sample_machines": [
        "achtung-gamma"
      ],
      "raw_users_seen": [
        "harshch1803"
      ]
    }
  },
  "cluster": {
    "total_capacity_accum": 16858255232,
    "samples": 26665,
    "last_capacity": 506176,
    "last_updated": "2025-11-12T17:00:02.547159Z"
  },
  "updated_at": "2025-11-12T17:00:02.547159Z"
}