{
  "users": {
    "Luze": {
      "total_mem_accum": 104154740,
      "total_gb_hours": 1695.2268880208333,
      "samples": 993,
      "avg_mem": 104888.96273917423,
      "last_sample_mem": 129918,
      "last_seen": "2025-10-26T20:35:02.755917Z",
      "first_seen": "2025-10-25T04:51:02.161833Z",
      "all_machines": [
        "achtung-biggpu"
      ],
      "last_sample_machines": [
        "achtung-biggpu"
      ],
      "raw_users_seen": [
        "luzsun"
      ]
    },
    "Shuyi": {
      "total_mem_accum": 189651586,
      "total_gb_hours": 3086.7771158854166,
      "samples": 1702,
      "avg_mem": 111428.66392479435,
      "last_sample_mem": 150940,
      "last_seen": "2025-10-26T20:35:02.755917Z",
      "first_seen": "2025-10-25T04:52:02.687274Z",
      "all_machines": [
        "achtung-gamma"
      ],
      "last_sample_machines": [
        "achtung-gamma"
      ],
      "raw_users_seen": [
        "shuyilin"
      ]
    },
    "Sae": {
      "total_mem_accum": 14335706,
      "total_gb_hours": 233.32854817708332,
      "samples": 231,
      "avg_mem": 62059.333333333336,
      "last_sample_mem": 58054,
      "last_seen": "2025-10-26T20:35:02.755917Z",
      "first_seen": "2025-10-25T04:52:02.687274Z",
      "all_machines": [
        "achtung-gamma"
      ],
      "last_sample_machines": [
        "achtung-gamma"
      ],
      "raw_users_seen": [
        "saefurukawa"
      ]
    },
    "Anshuman": {
      "total_mem_accum": 466102,
      "total_gb_hours": 7.586295572916667,
      "samples": 11,
      "avg_mem": 42372.90909090909,
      "last_sample_mem": 41740,
      "last_seen": "2025-10-25T19:11:02.872921Z",
      "first_seen": "2025-10-25T19:01:02.124980Z",
      "all_machines": [
        "achtung-gamma"
      ],
      "last_sample_machines": [
        "achtung-gamma"
      ],
      "raw_users_seen": [
        "anshumansuri"
      ]
    }
  },
  "cluster": {
    "total_capacity_accum": 1528479960,
    "samples": 2400,
    "last_capacity": 727288,
    "last_updated": "2025-10-26T20:35:02.755917Z"
  },
  "updated_at": "2025-10-26T20:35:02.755917Z"
}