{
  "users": {
    "Luze": {
      "total_mem_accum": 152528166,
      "total_gb_hours": 2482.55478515625,
      "samples": 1423,
      "avg_mem": 107187.74841883345,
      "last_sample_mem": 129930,
      "last_seen": "2025-10-27T06:30:02.541344Z",
      "first_seen": "2025-10-25T04:51:02.161833Z",
      "all_machines": [
        "achtung-biggpu",
        "achtung-biggpu (CPU)"
      ],
      "last_sample_machines": [
        "achtung-biggpu"
      ],
      "raw_users_seen": [
        "luzsun"
      ]
    },
    "Shuyi": {
      "total_mem_accum": 221529878,
      "total_gb_hours": 3605.6295247395833,
      "samples": 2082,
      "avg_mem": 106402.43900096061,
      "last_sample_mem": 86480,
      "last_seen": "2025-10-27T05:41:02.757004Z",
      "first_seen": "2025-10-25T04:52:02.687274Z",
      "all_machines": [
        "achtung-gamma"
      ],
      "last_sample_machines": [
        "achtung-gamma"
      ],
      "raw_users_seen": [
        "shuyilin"
      ]
    },
    "Sae": {
      "total_mem_accum": 79226012,
      "total_gb_hours": 1289.4858723958334,
      "samples": 826,
      "avg_mem": 95915.26876513317,
      "last_sample_mem": 58048,
      "last_seen": "2025-10-27T06:30:02.541344Z",
      "first_seen": "2025-10-25T04:52:02.687274Z",
      "all_machines": [
        "achtung-gamma"
      ],
      "last_sample_machines": [
        "achtung-gamma"
      ],
      "raw_users_seen": [
        "saefurukawa"
      ]
    },
    "Anshuman": {
      "total_mem_accum": 466102,
      "total_gb_hours": 7.586295572916667,
      "samples": 11,
      "avg_mem": 42372.90909090909,
      "last_sample_mem": 41740,
      "last_seen": "2025-10-25T19:11:02.872921Z",
      "first_seen": "2025-10-25T19:01:02.124980Z",
      "all_machines": [
        "achtung-gamma"
      ],
      "last_sample_machines": [
        "achtung-gamma"
      ],
      "raw_users_seen": [
        "anshumansuri"
      ]
    }
  },
  "cluster": {
    "total_capacity_accum": 1901319256,
    "samples": 2995,
    "last_capacity": 727288,
    "last_updated": "2025-10-27T06:30:02.541344Z"
  },
  "updated_at": "2025-10-27T06:30:02.541344Z"
}